sterope/__init__.py
sterope/_version.py
sterope/kasim.py
sterope/kasim3.py
sterope/roadrunner.py
sterope-1.5.dist-info/LICENSE.txt
sterope-1.5.dist-info/METADATA
sterope-1.5.dist-info/WHEEL
sterope-1.5.dist-info/top_level.txt
sterope-1.5.dist-info/RECORD
