Metadata-Version: 2.1
Name: sterope
Version: 1.5
Summary: Sterope: Sensitivity analysis of kappa Rule-Based Models based on Dynamic Influence Networks
Home-page: https://github.com/glucksfall/sterope
Author: Rodrigo Santibáñez
Author-email: glucksfall@users.noreply.github.com
License: GPLv3+
Project-URL: Manual, https://sterope.readthedocs.io
Project-URL: Bug Reports, https://github.com/glucksfall/sterope/issues
Project-URL: Source, https://github.com/glucksfall/sterope
Keywords: systems biology,stochastic modeling,parameter analysis
Platform: UNKNOWN
Classifier: Development Status :: 5 - Production/Stable
Classifier: Intended Audience :: Science/Research
Classifier: Topic :: Scientific/Engineering
Classifier: License :: OSI Approved :: GNU General Public License v3 or later (GPLv3+)
Classifier: Programming Language :: Python :: 3.6
Classifier: Programming Language :: Python :: 3.7
Classifier: Environment :: Console
Classifier: Operating System :: Unix
Requires-Python: >=3.0
Requires-Dist: numpy
Requires-Dist: pandas
Requires-Dist: salib
Requires-Dist: dask
Requires-Dist: dask-jobqueue
Requires-Dist: libroadrunner
